[
    {
        "name": "Gin",
        "confidence": 0.7756,
        "bbox": [
            489,
            335,
            553,
            571
        ],
        "position_3d": {
            "x": -0.166,
            "y": 0.1147,
            "z": 1.128
        },
        "id": 0
    },
    {
        "name": "JOHN BARR Whiskey",
        "confidence": 0.7074,
        "bbox": [
            543,
            335,
            615,
            600
        ],
        "position_3d": {
            "x": -0.0891,
            "y": 0.1246,
            "z": 1.064
        },
        "id": 1
    },
    {
        "name": "Plate",
        "confidence": 0.2544,
        "bbox": [
            175,
            543,
            430,
            660
        ],
        "position_3d": {
            "x": -0.4086,
            "y": 0.279,
            "z": 1.057
        },
        "id": 2
    },
    {
        "name": "Cola",
        "confidence": 0.7692,
        "bbox": [
            629,
            523,
            684,
            629
        ],
        "position_3d": {
            "x": 0.0004,
            "y": 0.2278,
            "z": 0.963
        },
        "id": 3
    },
    {
        "name": "Sprite",
        "confidence": 0.8212,
        "bbox": [
            691,
            568,
            759,
            689
        ],
        "position_3d": {
            "x": 0.0642,
            "y": 0.2486,
            "z": 0.847
        },
        "id": 4
    }
]